xadmin/__init__.py
xadmin/admin.py
xadmin/apps.py
xadmin/models.py
xadmin/tests.py
xadmin/views.py
xadmin/static/xadmin/app.css
xadmin/templates/xadmin/left_menu.html
django_admin_left_menu-0.1.1.dist-info/LICENSE
django_admin_left_menu-0.1.1.dist-info/METADATA
django_admin_left_menu-0.1.1.dist-info/WHEEL
django_admin_left_menu-0.1.1.dist-info/top_level.txt
django_admin_left_menu-0.1.1.dist-info/RECORD
