Metadata-Version: 2.1
Name: django-admin-left-menu
Version: 0.1.1
Summary: A simple left menu for DjangoAdmin
Home-page: https://github.com/ChanMo/django-admin-left-menu
Author: ChanMo
Author-email: chan.mo@outlook.com
License: BSD License
Platform: UNKNOWN
Classifier: Environment :: Web Environment
Classifier: Framework :: Django
Classifier: Framework :: Django :: 2.2
Classifier: Intended Audience :: Developers
Classifier: License :: OSI Approved :: BSD License
Classifier: Operating System :: OS Independent
Classifier: Programming Language :: Python
Classifier: Programming Language :: Python :: 3.5
Classifier: Programming Language :: Python :: 3.6
Classifier: Topic :: Internet :: WWW/HTTP
Classifier: Topic :: Internet :: WWW/HTTP :: Dynamic Content
